lap/__init__.py
lap/_lapjv.cpython-310-x86_64-linux-gnu.so
lap/lapmod.py
lap/tests/__init__.py
lap/tests/cost_eps.csv.gz
lap/tests/test_arr_loop.py
lap/tests/test_lapjv.py
lap/tests/test_lapmod.py
lap/tests/test_utils.py
tracklab_lap-0.5.dev0.dist-info/LICENSE
tracklab_lap-0.5.dev0.dist-info/METADATA
tracklab_lap-0.5.dev0.dist-info/WHEEL
tracklab_lap-0.5.dev0.dist-info/top_level.txt
tracklab_lap-0.5.dev0.dist-info/RECORD
